whatsapp_scraper/__init__.py
whatsapp_scraper/whatsapp_scraper.py
wpp_scraper-0.0.3.dist-info/LICENSE
wpp_scraper-0.0.3.dist-info/METADATA
wpp_scraper-0.0.3.dist-info/WHEEL
wpp_scraper-0.0.3.dist-info/top_level.txt
wpp_scraper-0.0.3.dist-info/RECORD
