Metadata-Version: 2.1
Name: wpp-scraper
Version: 0.0.3
Summary: The Most Powerful Contact Scraper for Whatsapp Web.
Author-email: João Tolovi <jhontolovi@gmail.com>
License: MIT License        
Project-URL: Homepage, https://github.com/joaotolovi/Whatsapp-Web-Scraper-
Classifier: Programming Language :: Python :: 3
Classifier: License :: OSI Approved :: MIT License
Classifier: Operating System :: OS Independent
Requires-Python: >=3.7
License-File: LICENSE
